{"success": true, "data": [{"id": "c6563232490fa8972a33d2df1a2e1301", "sport_key": "soccer_netherlands_eredivisie", "sport_nice": "Dutch Eredivisie", "teams": ["Ajax", "FC Volendam"], "home_team": "Ajax", "commence_time": "2023-11-02T19:01:04Z", "sites": [{"site_key": "pointsbetus", "site_nice": "PointsBet (US)", "last_update": "2023-11-02T20:48:07Z", "odds": {"h2h": [-3004, 10000, 1100]}}, {"site_key": "fanduel", "site_nice": "FanDuel", "last_update": "2023-11-02T20:48:34Z", "odds": {"h2h": [-3500, 10000, 1300]}}, {"site_key": "bovada", "site_nice": "Bovada", "last_update": "2023-11-02T20:57:38Z", "odds": {"h2h": [-2500, 12500, 900]}}, {"site_key": "barstool", "site_nice": "Barstool Sportsbook", "last_update": "2023-11-02T20:48:33Z", "odds": {"h2h": [-2000, 10000, 1100]}}], "sites_count": 4}, {"id": "667704133db203564280f60034296c94", "sport_key": "basketball_euroleague", "sport_nice": "Basketball Euroleague", "teams": ["AS Monaco", "Pallacanestro Olimpia Milano"], "home_team": "Pallacanestro Olimpia Milano", "commence_time": "2023-11-02T19:30:00Z", "sites": [{"site_key": "unibet_us", "site_nice": "Unibet", "last_update": "2023-11-02T21:01:52Z", "odds": {"h2h": [-127, -106]}}, {"site_key": "draftkings", "site_nice": "DraftKings", "last_update": "2023-11-02T21:01:52Z", "odds": {"h2h": [-115, -115]}}, {"site_key": "bovada", "site_nice": "Bovada", "last_update": "2023-11-02T21:01:53Z", "odds": {"h2h": [-230, 170]}}], "sites_count": 3}, {"id": "583b3f7a4818db285312e9efbb21c920", "sport_key": "basketball_euroleague", "sport_nice": "Basketball Euroleague", "teams": ["ALBA Berlin", "Valencia Basket"], "home_team": "Valencia Basket", "commence_time": "2023-11-02T19:30:59Z", "sites": [{"site_key": "draftkings", "site_nice": "DraftKings", "last_update": "2023-11-02T21:01:52Z", "odds": {"h2h": [105, -135]}}, {"site_key": "unibet_us", "site_nice": "Unibet", "last_update": "2023-11-02T21:01:52Z", "odds": {"h2h": [128, -175]}}, {"site_key": "bovada", "site_nice": "Bovada", "last_update": "2023-11-02T21:01:53Z", "odds": {"h2h": [170, -230]}}], "sites_count": 3}, {"id": "82d555d0072d063169f68aaa3b9bd198", "sport_key": "soccer_brazil_campeonato", "sport_nice": "Brazil S\u00e9rie A", "teams": ["Cuiab\u00e1", "Vasco da Gama"], "home_team": "Cuiab\u00e1", "commence_time": "2023-11-02T20:01:05Z", "sites": [{"site_key": "unibet_us", "site_nice": "Unibet", "last_update": "2023-11-02T21:01:58Z", "odds": {"h2h": [200, 275, 107]}}, {"site_key": "pointsbetus", "site_nice": "PointsBet (US)", "last_update": "2023-11-02T21:02:35Z", "odds": {"h2h": [180, 290, 110]}}, {"site_key": "mybookieag", "site_nice": "MyBookie.ag", "last_update": "2023-11-02T21:01:57Z", "odds": {"h2h": [170, 230, 125]}}, {"site_key": "fanduel", "site_nice": "FanDuel", "last_update": "2023-11-02T21:01:37Z", "odds": {"h2h": [198, 270, 110]}}, {"site_key": "bovada", "site_nice": "Bovada", "last_update": "2023-11-02T21:01:57Z", "odds": {"h2h": [195, 280, 114]}}, {"site_key": "draftkings", "site_nice": "DraftKings", "last_update": "2023-11-02T21:01:57Z", "odds": {"h2h": [185, 300, 115]}}, {"site_key": "barstool", "site_nice": "Barstool Sportsbook", "last_update": "2023-11-02T21:01:57Z", "odds": {"h2h": [200, 290, 110]}}], "sites_count": 7}, {"id": "f59524fa69763eb7e42b13fd2c27788d", "sport_key": "soccer_brazil_campeonato", "sport_nice": "Brazil S\u00e9rie A", "teams": ["Bragantino-SP", "Goi\u00e1s"], "home_team": "Goi\u00e1s", "commence_time": "2023-11-02T20:59:42Z", "sites": [{"site_key": "betrivers", "site_nice": "BetRivers", "last_update": "2023-11-02T20:48:21Z", "odds": {"h2h": [115, 240, 240]}}, {"site_key": "unibet_us", "site_nice": "Unibet", "last_update": "2023-11-02T21:01:58Z", "odds": {"h2h": [123, 215, 225]}}, {"site_key": "superbook", "site_nice": "SuperBook", "last_update": "2023-11-02T20:59:10Z", "odds": {"h2h": [130, 205, 225]}}, {"site_key": "pointsbetus", "site_nice": "PointsBet (US)", "last_update": "2023-11-02T21:02:35Z", "odds": {"h2h": [110, 230, 225]}}, {"site_key": "mybookieag", "site_nice": "MyBookie.ag", "last_update": "2023-11-02T21:01:57Z", "odds": {"h2h": [129, 210, 230]}}, {"site_key": "fanduel", "site_nice": "FanDuel", "last_update": "2023-11-02T21:01:37Z", "odds": {"h2h": [114, 230, 225]}}, {"site_key": "bovada", "site_nice": "Bovada", "last_update": "2023-11-02T21:01:57Z", "odds": {"h2h": [130, 215, 240]}}, {"site_key": "draftkings", "site_nice": "DraftKings", "last_update": "2023-11-02T21:01:57Z", "odds": {"h2h": [125, 220, 225]}}, {"site_key": "barstool", "site_nice": "Barstool Sportsbook", "last_update": "2023-11-02T21:01:57Z", "odds": {"h2h": [120, 225, 225]}}, {"site_key": "betonlineag", "site_nice": "BetOnline.ag", "last_update": "2023-11-02T20:59:27Z", "odds": {"h2h": [125, 222, 240]}}, {"site_key": "lowvig", "site_nice": "LowVig.ag", "last_update": "2023-11-02T20:59:13Z", "odds": {"h2h": [125, 222, 240]}}, {"site_key": "betus", "site_nice": "BetUS", "last_update": "2023-11-02T20:59:10Z", "odds": {"h2h": [125, 220, 240]}}], "sites_count": 12}, {"id": "bf8b67194bcae7db579a6d32a7070f80", "sport_key": "basketball_nba", "sport_nice": "NBA", "teams": ["Philadelphia 76ers", "Toronto Raptors"], "home_team": "Philadelphia 76ers", "commence_time": "2023-11-02T23:00:00Z", "sites": [{"site_key": "twinspires", "site_nice": "TwinSpires", "last_update": "2023-11-02T21:01:30Z", "odds": {"h2h": [-375, 280]}}, {"site_key": "unibet_us", "site_nice": "Unibet", "last_update": "2023-11-02T21:01:30Z", "odds": {"h2h": [-375, 280]}}, {"site_key": "betrivers", "site_nice": "BetRivers", "last_update": "2023-11-02T21:01:29Z", "odds": {"h2h": [-375, 280]}}, {"site_key": "betmgm", "site_nice": "BetMGM", "last_update": "2023-11-02T21:01:29Z", "odds": {"h2h": [-350, 260]}}, {"site_key": "fanduel", "site_nice": "FanDuel", "last_update": "2023-11-02T21:02:19Z", "odds": {"h2h": [-330, 265]}}, {"site_key": "pointsbetus", "site_nice": "PointsBet (US)", "last_update": "2023-11-02T21:01:29Z", "odds": {"h2h": [-350, 260]}}, {"site_key": "bovada", "site_nice": "Bovada", "last_update": "2023-11-02T21:01:29Z", "odds": {"h2h": [-320, 260]}}, {"site_key": "barstool", "site_nice": "Barstool Sportsbook", "last_update": "2023-11-02T21:01:30Z", "odds": {"h2h": [-340, 270]}}, {"site_key": "betonlineag", "site_nice": "BetOnline.ag", "last_update": "2023-11-02T21:02:18Z", "odds": {"h2h": [-312, 260]}}, {"site_key": "lowvig", "site_nice": "LowVig.ag", "last_update": "2023-11-02T21:02:21Z", "odds": {"h2h": [-310, 260]}}, {"site_key": "wynnbet", "site_nice": "WynnBET", "last_update": "2023-11-02T21:01:50Z", "odds": {"h2h": [-312, 252]}}, {"site_key": "williamhill_us", "site_nice": "Caesars", "last_update": "2023-11-02T21:00:49Z", "odds": {"h2h": [-320, 250]}}, {"site_key": "draftkings", "site_nice": "DraftKings", "last_update": "2023-11-02T21:02:18Z", "odds": {"h2h": [-340, 270]}}, {"site_key": "mybookieag", "site_nice": "MyBookie.ag", "last_update": "2023-11-02T21:02:18Z", "odds": {"h2h": [-300, 250]}}, {"site_key": "betus", "site_nice": "BetUS", "last_update": "2023-11-02T21:01:29Z", "odds": {"h2h": [-325, 265]}}, {"site_key": "superbook", "site_nice": "SuperBook", "last_update": "2023-11-02T21:01:31Z", "odds": {"h2h": [-330, 260]}}], "sites_count": 16}, {"id": "cd795b9e845200459b078827ea6b8daa", "sport_key": "icehockey_nhl", "sport_nice": "NHL", "teams": ["New York Islanders", "Washington Capitals"], "home_team": "Washington Capitals", "commence_time": "2023-11-02T23:00:00Z", "sites": [{"site_key": "twinspires", "site_nice": "TwinSpires", "last_update": "2023-11-02T21:01:32Z", "odds": {"h2h": [-117, -104]}}, {"site_key": "unibet_us", "site_nice": "Unibet", "last_update": "2023-11-02T21:01:32Z", "odds": {"h2h": [-117, -104]}}, {"site_key": "betrivers", "site_nice": "BetRivers", "last_update": "2023-11-02T21:02:32Z", "odds": {"h2h": [-117, -104]}}, {"site_key": "betonlineag", "site_nice": "BetOnline.ag", "last_update": "2023-11-02T21:02:31Z", "odds": {"h2h": [-118, 105]}}, {"site_key": "lowvig", "site_nice": "LowVig.ag", "last_update": "2023-11-02T21:02:34Z", "odds": {"h2h": [-118, 105]}}, {"site_key": "draftkings", "site_nice": "DraftKings", "last_update": "2023-11-02T21:01:31Z", "odds": {"h2h": [-120, 100]}}, {"site_key": "williamhill_us", "site_nice": "Caesars", "last_update": "2023-11-02T21:01:03Z", "odds": {"h2h": [-120, 100]}}, {"site_key": "fanduel", "site_nice": "FanDuel", "last_update": "2023-11-02T21:02:32Z", "odds": {"h2h": [-118, -102]}}, {"site_key": "betus", "site_nice": "BetUS", "last_update": "2023-11-02T21:01:32Z", "odds": {"h2h": [-125, 105]}}, {"site_key": "betmgm", "site_nice": "BetMGM", "last_update": "2023-11-02T21:01:33Z", "odds": {"h2h": [-120, 100]}}, {"site_key": "superbook", "site_nice": "SuperBook", "last_update": "2023-11-02T21:01:32Z", "odds": {"h2h": [-116, 100]}}, {"site_key": "barstool", "site_nice": "Barstool Sportsbook", "last_update": "2023-11-02T21:01:33Z", "odds": {"h2h": [-120, 100]}}, {"site_key": "pointsbetus", "site_nice": "PointsBet (US)", "last_update": "2023-11-02T21:01:31Z", "odds": {"h2h": [-115, -105]}}, {"site_key": "bovada", "site_nice": "Bovada", "last_update": "2023-11-02T21:01:32Z", "odds": {"h2h": [-125, 105]}}], "sites_count": 14}, {"id": "02b2e8e4eb8aad92b4adc15f85ba057f", "sport_key": "americanfootball_ncaaf", "sport_nice": "NCAAF", "teams": ["TCU Horned Frogs", "Texas Tech Red Raiders"], "home_team": "Texas Tech Red Raiders", "commence_time": "2023-11-02T23:00:00Z", "sites": [{"site_key": "draftkings", "site_nice": "DraftKings", "last_update": "2023-11-02T21:00:28Z", "odds": {"h2h": [114, -135]}}, {"site_key": "fanduel", "site_nice": "FanDuel", "last_update": "2023-11-02T21:01:44Z", "odds": {"h2h": [114, -137]}}, {"site_key": "lowvig", "site_nice": "LowVig.ag", "last_update": "2023-11-02T21:02:09Z", "odds": {"h2h": [119, -139]}}, {"site_key": "pointsbetus", "site_nice": "PointsBet (US)", "last_update": "2023-11-02T21:02:02Z", "odds": {"h2h": [120, -140]}}, {"site_key": "unibet_us", "site_nice": "Unibet", "last_update": "2023-11-02T21:01:42Z", "odds": {"h2h": [118, -143]}}, {"site_key": "bovada", "site_nice": "Bovada", "last_update": "2023-11-02T21:01:42Z", "odds": {"h2h": [120, -140]}}, {"site_key": "betmgm", "site_nice": "BetMGM", "last_update": "2023-11-02T21:02:03Z", "odds": {"h2h": [120, -145]}}, {"site_key": "williamhill_us", "site_nice": "Caesars", "last_update": "2023-11-02T21:02:02Z", "odds": {"h2h": [118, -140]}}, {"site_key": "betrivers", "site_nice": "BetRivers", "last_update": "2023-11-02T20:59:35Z", "odds": {"h2h": [118, -143]}}, {"site_key": "betonlineag", "site_nice": "BetOnline.ag", "last_update": "2023-11-02T21:02:40Z", "odds": {"h2h": [119, -139]}}, {"site_key": "superbook", "site_nice": "SuperBook", "last_update": "2023-11-02T21:01:43Z", "odds": {"h2h": [120, -140]}}, {"site_key": "betus", "site_nice": "BetUS", "last_update": "2023-11-02T21:02:02Z", "odds": {"h2h": [120, -140]}}, {"site_key": "barstool", "site_nice": "Barstool Sportsbook", "last_update": "2023-11-02T21:01:42Z", "odds": {"h2h": [120, -140]}}, {"site_key": "mybookieag", "site_nice": "MyBookie.ag", "last_update": "2023-11-02T21:01:41Z", "odds": {"h2h": [120, -140]}}], "sites_count": 14}, {"id": "96c255a30e4bb3328b20ad602aebb02e", "sport_key": "icehockey_nhl", "sport_nice": "NHL", "teams": ["Columbus Blue Jackets", "Tampa Bay Lightning"], "home_team": "Columbus Blue Jackets", "commence_time": "2023-11-02T23:00:00Z", "sites": [{"site_key": "unibet_us", "site_nice": "Unibet", "last_update": "2023-11-02T21:01:32Z", "odds": {"h2h": [128, -157]}}, {"site_key": "twinspires", "site_nice": "TwinSpires", "last_update": "2023-11-02T21:01:32Z", "odds": {"h2h": [128, -157]}}, {"site_key": "betrivers", "site_nice": "BetRivers", "last_update": "2023-11-02T21:02:32Z", "odds": {"h2h": [128, -157]}}, {"site_key": "betonlineag", "site_nice": "BetOnline.ag", "last_update": "2023-11-02T21:02:31Z", "odds": {"h2h": [137, -154]}}, {"site_key": "lowvig", "site_nice": "LowVig.ag", "last_update": "2023-11-02T21:02:34Z", "odds": {"h2h": [137, -154]}}, {"site_key": "draftkings", "site_nice": "DraftKings", "last_update": "2023-11-02T21:01:31Z", "odds": {"h2h": [136, -162]}}, {"site_key": "williamhill_us", "site_nice": "Caesars", "last_update": "2023-11-02T21:01:03Z", "odds": {"h2h": [135, -160]}}, {"site_key": "fanduel", "site_nice": "FanDuel", "last_update": "2023-11-02T21:02:32Z", "odds": {"h2h": [126, -152]}}, {"site_key": "betus", "site_nice": "BetUS", "last_update": "2023-11-02T21:01:32Z", "odds": {"h2h": [140, -160]}}, {"site_key": "betmgm", "site_nice": "BetMGM", "last_update": "2023-11-02T21:01:33Z", "odds": {"h2h": [135, -160]}}, {"site_key": "superbook", "site_nice": "SuperBook", "last_update": "2023-11-02T21:01:32Z", "odds": {"h2h": [140, -160]}}, {"site_key": "barstool", "site_nice": "Barstool Sportsbook", "last_update": "2023-11-02T21:01:33Z", "odds": {"h2h": [135, -165]}}, {"site_key": "pointsbetus", "site_nice": "PointsBet (US)", "last_update": "2023-11-02T21:01:31Z", "odds": {"h2h": [130, -160]}}, {"site_key": "bovada", "site_nice": "Bovada", "last_update": "2023-11-02T21:01:32Z", "odds": {"h2h": [135, -160]}}], "sites_count": 14}, {"id": "f4b745aa807710be1c56d1c99a65f0cf", "sport_key": "icehockey_nhl", "sport_nice": "NHL", "teams": ["Los Angeles Kings", "Ottawa Senators"], "home_team": "Ottawa Senators", "commence_time": "2023-11-02T23:00:00Z", "sites": [{"site_key": "twinspires", "site_nice": "TwinSpires", "last_update": "2023-11-02T21:01:32Z", "odds": {"h2h": [-110, -110]}}, {"site_key": "unibet_us", "site_nice": "Unibet", "last_update": "2023-11-02T21:01:32Z", "odds": {"h2h": [-110, -110]}}, {"site_key": "betrivers", "site_nice": "BetRivers", "last_update": "2023-11-02T21:02:32Z", "odds": {"h2h": [-110, -110]}}, {"site_key": "betonlineag", "site_nice": "BetOnline.ag", "last_update": "2023-11-02T21:02:31Z", "odds": {"h2h": [-111, -101]}}, {"site_key": "lowvig", "site_nice": "LowVig.ag", "last_update": "2023-11-02T21:02:34Z", "odds": {"h2h": [-111, -101]}}, {"site_key": "draftkings", "site_nice": "DraftKings", "last_update": "2023-11-02T21:01:31Z", "odds": {"h2h": [-112, -108]}}, {"site_key": "williamhill_us", "site_nice": "Caesars", "last_update": "2023-11-02T21:01:03Z", "odds": {"h2h": [-110, -110]}}, {"site_key": "fanduel", "site_nice": "FanDuel", "last_update": "2023-11-02T21:02:32Z", "odds": {"h2h": [-115, -104]}}, {"site_key": "betus", "site_nice": "BetUS", "last_update": "2023-11-02T21:01:32Z", "odds": {"h2h": [-115, -105]}}, {"site_key": "betmgm", "site_nice": "BetMGM", "last_update": "2023-11-02T21:01:33Z", "odds": {"h2h": [-115, -105]}}, {"site_key": "superbook", "site_nice": "SuperBook", "last_update": "2023-11-02T21:01:32Z", "odds": {"h2h": [-110, -106]}}, {"site_key": "barstool", "site_nice": "Barstool Sportsbook", "last_update": "2023-11-02T21:01:33Z", "odds": {"h2h": [-110, -110]}}, {"site_key": "pointsbetus", "site_nice": "PointsBet (US)", "last_update": "2023-11-02T21:01:31Z", "odds": {"h2h": [-110, -110]}}, {"site_key": "bovada", "site_nice": "Bovada", "last_update": "2023-11-02T21:01:32Z", "odds": {"h2h": [-120, 100]}}], "sites_count": 14}, {"id": "c930b1f26e19b70d75c700fe674eaaad", "sport_key": "soccer_brazil_campeonato", "sport_nice": "Brazil S\u00e9rie A", "teams": ["Cruzeiro", "Sao Paulo"], "home_team": "Sao Paulo", "commence_time": "2023-11-02T23:00:00Z", "sites": [{"site_key": "betrivers", "site_nice": "BetRivers", "last_update": "2023-11-02T21:01:57Z", "odds": {"h2h": [420, -132, 240]}}, {"site_key": "betmgm", "site_nice": "BetMGM", "last_update": "2023-11-02T21:02:36Z", "odds": {"h2h": [350, -110, 220]}}, {"site_key": "unibet_us", "site_nice": "Unibet", "last_update": "2023-11-02T21:01:58Z", "odds": {"h2h": [420, -132, 240]}}, {"site_key": "pointsbetus", "site_nice": "PointsBet (US)", "last_update": "2023-11-02T21:02:35Z", "odds": {"h2h": [400, -125, 225]}}, {"site_key": "fanduel", "site_nice": "FanDuel", "last_update": "2023-11-02T21:01:37Z", "odds": {"h2h": [380, -130, 230]}}, {"site_key": "mybookieag", "site_nice": "MyBookie.ag", "last_update": "2023-11-02T21:01:57Z", "odds": {"h2h": [360, -118, 230]}}, {"site_key": "superbook", "site_nice": "SuperBook", "last_update": "2023-11-02T21:01:58Z", "odds": {"h2h": [345, -115, 225]}}, {"site_key": "bovada", "site_nice": "Bovada", "last_update": "2023-11-02T21:01:57Z", "odds": {"h2h": [375, -115, 240]}}, {"site_key": "draftkings", "site_nice": "DraftKings", "last_update": "2023-11-02T21:01:57Z", "odds": {"h2h": [340, -110, 235]}}, {"site_key": "barstool", "site_nice": "Barstool Sportsbook", "last_update": "2023-11-02T21:01:57Z", "odds": {"h2h": [350, -115, 230]}}, {"site_key": "betonlineag", "site_nice": "BetOnline.ag", "last_update": "2023-11-02T21:02:36Z", "odds": {"h2h": [385, -120, 235]}}, {"site_key": "lowvig", "site_nice": "LowVig.ag", "last_update": "2023-11-02T21:02:38Z", "odds": {"h2h": [385, -120, 235]}}, {"site_key": "betus", "site_nice": "BetUS", "last_update": "2023-11-02T21:02:36Z", "odds": {"h2h": [400, -130, 245]}}], "sites_count": 13}, {"id": "71ddec1fdacb96e4a07cdc8b35ead0a7", "sport_key": "icehockey_nhl", "sport_nice": "NHL", "teams": ["Detroit Red Wings", "Florida Panthers"], "home_team": "Detroit Red Wings", "commence_time": "2023-11-02T23:00:00Z", "sites": [{"site_key": "unibet_us", "site_nice": "Unibet", "last_update": "2023-11-02T21:01:32Z", "odds": {"h2h": [102, -125]}}, {"site_key": "twinspires", "site_nice": "TwinSpires", "last_update": "2023-11-02T21:01:32Z", "odds": {"h2h": [102, -125]}}, {"site_key": "betrivers", "site_nice": "BetRivers", "last_update": "2023-11-02T21:02:32Z", "odds": {"h2h": [102, -125]}}, {"site_key": "betonlineag", "site_nice": "BetOnline.ag", "last_update": "2023-11-02T21:02:31Z", "odds": {"h2h": [104, -116]}}, {"site_key": "lowvig", "site_nice": "LowVig.ag", "last_update": "2023-11-02T21:02:34Z", "odds": {"h2h": [104, -117]}}, {"site_key": "draftkings", "site_nice": "DraftKings", "last_update": "2023-11-02T21:01:31Z", "odds": {"h2h": [100, -120]}}, {"site_key": "williamhill_us", "site_nice": "Caesars", "last_update": "2023-11-02T21:01:03Z", "odds": {"h2h": [100, -120]}}, {"site_key": "fanduel", "site_nice": "FanDuel", "last_update": "2023-11-02T21:02:32Z", "odds": {"h2h": [100, -120]}}, {"site_key": "betus", "site_nice": "BetUS", "last_update": "2023-11-02T21:01:32Z", "odds": {"h2h": [100, -120]}}, {"site_key": "betmgm", "site_nice": "BetMGM", "last_update": "2023-11-02T21:01:33Z", "odds": {"h2h": [100, -120]}}, {"site_key": "superbook", "site_nice": "SuperBook", "last_update": "2023-11-02T21:01:32Z", "odds": {"h2h": [101, -117]}}, {"site_key": "barstool", "site_nice": "Barstool Sportsbook", "last_update": "2023-11-02T21:01:33Z", "odds": {"h2h": [100, -120]}}, {"site_key": "pointsbetus", "site_nice": "PointsBet (US)", "last_update": "2023-11-02T21:01:31Z", "odds": {"h2h": [100, -120]}}, {"site_key": "bovada", "site_nice": "Bovada", "last_update": "2023-11-02T21:01:32Z", "odds": {"h2h": [105, -125]}}], "sites_count": 14}, {"id": "45e4da473a8b3d2e2973e49b276835d3", "sport_key": "icehockey_nhl", "sport_nice": "NHL", "teams": ["Carolina Hurricanes", "New York Rangers"], "home_team": "New York Rangers", "commence_time": "2023-11-02T23:00:00Z", "sites": [{"site_key": "twinspires", "site_nice": "TwinSpires", "last_update": "2023-11-02T21:01:32Z", "odds": {"h2h": [-105, -115]}}, {"site_key": "unibet_us", "site_nice": "Unibet", "last_update": "2023-11-02T21:01:32Z", "odds": {"h2h": [-105, -115]}}, {"site_key": "betrivers", "site_nice": "BetRivers", "last_update": "2023-11-02T21:02:32Z", "odds": {"h2h": [-105, -115]}}, {"site_key": "betonlineag", "site_nice": "BetOnline.ag", "last_update": "2023-11-02T21:02:31Z", "odds": {"h2h": [-101, -111]}}, {"site_key": "lowvig", "site_nice": "LowVig.ag", "last_update": "2023-11-02T21:02:34Z", "odds": {"h2h": [-101, -111]}}, {"site_key": "draftkings", "site_nice": "DraftKings", "last_update": "2023-11-02T21:01:31Z", "odds": {"h2h": [-105, -115]}}, {"site_key": "williamhill_us", "site_nice": "Caesars", "last_update": "2023-11-02T21:01:03Z", "odds": {"h2h": [-105, -115]}}, {"site_key": "fanduel", "site_nice": "FanDuel", "last_update": "2023-11-02T21:02:32Z", "odds": {"h2h": [-104, -115]}}, {"site_key": "betus", "site_nice": "BetUS", "last_update": "2023-11-02T21:01:32Z", "odds": {"h2h": [-105, -115]}}, {"site_key": "betmgm", "site_nice": "BetMGM", "last_update": "2023-11-02T21:01:33Z", "odds": {"h2h": [-105, -115]}}, {"site_key": "superbook", "site_nice": "SuperBook", "last_update": "2023-11-02T21:01:32Z", "odds": {"h2h": [100, -116]}}, {"site_key": "barstool", "site_nice": "Barstool Sportsbook", "last_update": "2023-11-02T21:01:33Z", "odds": {"h2h": [-105, -115]}}, {"site_key": "pointsbetus", "site_nice": "PointsBet (US)", "last_update": "2023-11-02T21:01:31Z", "odds": {"h2h": [-110, -110]}}, {"site_key": "bovada", "site_nice": "Bovada", "last_update": "2023-11-02T21:01:32Z", "odds": {"h2h": [-105, -115]}}], "sites_count": 14}]}